{"SIGNATURE":"zSdHmJ6+fMoho/5vJBzV0xrwazEcJMWKT9iQl6pfv3+HEGBjPW/v3UMektVCf2yAVy3E5kmR+yOA4vQ5g0LFCw==","validThru":"2020-05-10T04:09:28+00:00","channels":[{"channel":"release","channelConditional":"GIT_TAG =~ \".+\"","releases":[{"buildPropertyMatch":"!(GIT_TAG =~ \"3.3.0\") && (PLATFORM =~ \"Windows|Mac OS X|Linux|.*\")","version":"3.3.0","published_at":"2019-08-31T20:16:52Z","notification":{"base":"release_update","id":"3.3.0"},"updateLink":"https://wz2100.net/?platform={{PLATFORM}}"}]},{"channel":"development","channelConditional":"(GIT_BRANCH =~ \"^master$\") && !(GIT_TAG =~ \".+\")","releases":[{"buildPropertyMatch":"!(GIT_FULL_HASH =~ \"52e9bb3cf00cf01bb779e816f426f51bb9a12203\")","version":"master_52e9bb3","published_at":"2020-05-09T02:38:50Z","notification":{"base":"dev_update","id":"master_52e9bb3"},"updateLink":"https://github.com/Warzone2100/warzone2100/blob/master/README.md#latest-development-builds"}]}]}
