{"SIGNATURE":"NifA67L36FVmAnuI1SzBSFCZtL4mIH8pDC0ryfH75pR3o4XCOKsr0+uts5gxF9fPgPQlPf7ZbcFjwHn46FUgBA==","validThru":"2020-05-17T23:05:00+00:00","channels":[{"channel":"release","channelConditional":"GIT_TAG =~ \".+\"","releases":[{"buildPropertyMatch":"!(GIT_TAG =~ \"3.3.0\") && (PLATFORM =~ \"Windows|Mac OS X|Linux|.*\")","version":"3.3.0","published_at":"2019-08-31T20:16:52Z","notification":{"base":"release_update","id":"3.3.0"},"updateLink":"https://wz2100.net/?platform={{PLATFORM}}"}]},{"channel":"development","channelConditional":"(GIT_BRANCH =~ \"^master$\") && !(GIT_TAG =~ \".+\")","releases":[{"buildPropertyMatch":"!(GIT_FULL_HASH =~ \"0150bcd7cb8930530352916a669badae583d9d09\")","version":"master_0150bcd","published_at":"2020-05-15T13:52:26Z","notification":{"base":"dev_update","id":"master_0150bcd"},"updateLink":"https://github.com/Warzone2100/warzone2100/blob/master/README.md#latest-development-builds"}]}]}
