{"SIGNATURE":"6rhVtd2NC1unmQCAgxr8bB/OuHCIG5mt2uNoL1nQBFbvtb6JM+xlZACkIb2dlOwIlfZIDdNYfBQ0Wfe4GBD+AA==","validThru":"2020-09-24T08:04:10+00:00","channels":[{"channel":"release","channelConditional":"GIT_TAG =~ \".+\"","releases":[{"buildPropertyMatch":"!(GIT_TAG =~ \"3.4.1\") && (PLATFORM =~ \"Windows|Mac OS X|Linux|.*\") && (WZ_PACKAGE_DISTRIBUTOR =~ \"^wz2100.net$\")","version":"3.4.1","published_at":"2020-07-19T17:37:37Z","notification":{"base":"release_update","id":"3.4.1"},"updateLink":"https://wz2100.net/?platform={{PLATFORM}}"}]},{"channel":"development","channelConditional":"(GIT_BRANCH =~ \"^master$\") && !(GIT_TAG =~ \".+\") && (WZ_PACKAGE_DISTRIBUTOR =~ \"^wz2100.net$\")","releases":[{"buildPropertyMatch":"!(GIT_FULL_HASH =~ \"94411e0745df505b9ce8eb0459fcac95adca194b\")","version":"master_94411e0","published_at":"2020-09-20T07:12:44Z","notification":{"base":"dev_update","id":"master_94411e0"},"updateLink":"https://github.com/Warzone2100/warzone2100/blob/master/README.md#latest-development-builds"}]}]}
