{"SIGNATURE":"QNrzMQcVXvfkBisqqzX7KISSqod6X6lUhgvrxzy/QRiX3/lcCpPEXkaDUxVdZdg3OTSqqlBMdXA8yDhgVC6LDw==","validThru":"2020-08-25T23:09:06+00:00","channels":[{"channel":"release","channelConditional":"GIT_TAG =~ \".+\"","releases":[{"buildPropertyMatch":"!(GIT_TAG =~ \"3.4.1\") && (PLATFORM =~ \"Windows|Mac OS X|Linux|.*\") && (WZ_PACKAGE_DISTRIBUTOR =~ \"^wz2100.net$\")","version":"3.4.1","published_at":"2020-07-19T17:37:37Z","notification":{"base":"release_update","id":"3.4.1"},"updateLink":"https://wz2100.net/?platform={{PLATFORM}}"}]},{"channel":"development","channelConditional":"(GIT_BRANCH =~ \"^master$\") && !(GIT_TAG =~ \".+\") && (WZ_PACKAGE_DISTRIBUTOR =~ \"^wz2100.net$\")","releases":[{"buildPropertyMatch":"!(GIT_FULL_HASH =~ \"1eb9740cdc336dca31ceab258375b3232e2d3957\")","version":"master_1eb9740","published_at":"2020-08-21T18:26:08Z","notification":{"base":"dev_update","id":"master_1eb9740"},"updateLink":"https://github.com/Warzone2100/warzone2100/blob/master/README.md#latest-development-builds"}]}]}
